CHANGES.md
LICENSE
MANIFEST.in
README.md
setup.py
uniapi/__init__.py
uniapi/__main__.py
uniapi/uniapi.py
uniapi.egg-info/PKG-INFO
uniapi.egg-info/SOURCES.txt
uniapi.egg-info/dependency_links.txt
uniapi.egg-info/not-zip-safe
uniapi.egg-info/requires.txt
uniapi.egg-info/top_level.txt