Metadata-Version: 2.1
Name: uniapi
Version: 1.0.7
Summary: A Universal API Framework.
Home-page: https://github.com/sintrb/uniapi/
Author: trb
Author-email: sintrb@gmail.com
License: UNKNOWN
Keywords: uniapi
Platform: UNKNOWN
